meno/__init__.py
meno/default_config.yaml
meno/llm_manual_usage_example.py
meno/meno.py
meno/web_interface.py
meno/workflow.py
meno/active_learning/__init__.py
meno/active_learning/cleanlab_wrapper.py
meno/active_learning/simple_feedback.py
meno/cli/__init__.py
meno/cli/team_config_cli.py
meno/cli/web_interface_cli.py
meno/modeling/__init__.py
meno/modeling/base.py
meno/modeling/bertopic_model.py
meno/modeling/bertopic_optimizer.py
meno/modeling/coherence.py
meno/modeling/embeddings.py
meno/modeling/llm_topic_labeling.py
meno/modeling/llm_topic_labeling_extended.py
meno/modeling/streaming_processor.py
meno/modeling/supervised.py
meno/modeling/top2vec_model.py
meno/modeling/unified_topic_modeling.py
meno/modeling/unsupervised.py
meno/modeling/simple_models/__init__.py
meno/modeling/simple_models/lightweight_models.py
meno/preprocessing/__init__.py
meno/preprocessing/acronyms.py
meno/preprocessing/deduplication.py
meno/preprocessing/normalization.py
meno/preprocessing/spelling.py
meno/reporting/__init__.py
meno/reporting/html_generator.py
meno/utils/__init__.py
meno/utils/config.py
meno/utils/llm_providers.py
meno/utils/team_config.py
meno/visualization/__init__.py
meno/visualization/bertopic_viz.py
meno/visualization/geospatial.py
meno/visualization/interactive_plots.py
meno/visualization/lightweight_viz.py
meno/visualization/static_plots.py
meno/visualization/time_series.py
meno/visualization/time_space.py
meno/visualization/umap_viz.py
meno/visualization/enhanced_viz/__init__.py
meno/visualization/enhanced_viz/comparative_viz.py
meno/visualization/enhanced_viz/entity_flow.py
meno/visualization/enhanced_viz/feedback_viz.py
meno/visualization/enhanced_viz/interactive_viz.py
meno-1.3.5.dist-info/licenses/LICENSE
meno-1.3.5.dist-info/METADATA
meno-1.3.5.dist-info/WHEEL
meno-1.3.5.dist-info/entry_points.txt
meno-1.3.5.dist-info/top_level.txt
meno-1.3.5.dist-info/RECORD
