Metadata-Version: 2.4
Name: meno
Version: 1.3.5
Summary: Topic modeling toolkit for messy text data
Home-page: https://github.com/srepho/meno
Author: Stephen Oates
Author-email: Stephen Oates <stephen.oates@example.com>
License: MIT
Project-URL: Homepage, https://github.com/srepho/meno
Project-URL: Bug Tracker, https://github.com/srepho/meno/issues
Classifier: Development Status :: 3 - Alpha
Classifier: Intended Audience :: Science/Research
Classifier: License :: OSI Approved :: MIT License
Classifier: Programming Language :: Python :: 3
Classifier: Programming Language :: Python :: 3.9
Classifier: Programming Language :: Python :: 3.10
Classifier: Programming Language :: Python :: 3.11
Classifier: Programming Language :: Python :: 3.12
Classifier: Programming Language :: Python :: 3.13
Classifier: Topic :: Scientific/Engineering :: Artificial Intelligence
Classifier: Topic :: Text Processing :: Linguistic
Requires-Python: >=3.9,<3.14
License-File: LICENSE
Requires-Dist: pandas<3.0.0,>=2.0.0
Requires-Dist: pyarrow>=11.0.0
Requires-Dist: scikit-learn<2.0.0,>=1.2.0
Requires-Dist: pydantic<3.0.0,>=2.0.0
Requires-Dist: pyyaml<7.0,>=6.0
Requires-Dist: jinja2<4.0.0,>=3.1.2
Requires-Dist: thefuzz<0.21.0,>=0.20.0
Requires-Dist: argparse<2.0.0,>=1.4.0
Provides-Extra: lightweight
Requires-Dist: scikit-learn<2.0.0,>=1.2.0; extra == "lightweight"
Requires-Dist: plotly<6.0.0,>=5.14.0; extra == "lightweight"
Requires-Dist: wordcloud<2.0.0,>=1.9.0; extra == "lightweight"
Provides-Extra: cpu
Requires-Dist: sentence-transformers<3.0.0,>=2.2.2; extra == "cpu"
Requires-Dist: transformers<5.0.0,>=4.28.0; extra == "cpu"
Requires-Dist: torch<3.0.0,>=2.0.0; extra == "cpu"
Requires-Dist: plotly<6.0.0,>=5.14.0; extra == "cpu"
Requires-Dist: umap-learn<0.6.0,>=0.5.3; extra == "cpu"
Requires-Dist: hdbscan<0.9.0,>=0.8.29; extra == "cpu"
Requires-Dist: bertopic<0.16.0,>=0.15.0; extra == "cpu"
Requires-Dist: gensim<5.0.0,>=4.3.0; extra == "cpu"
Requires-Dist: spacy<4.0.0,>=3.5.0; extra == "cpu"
Requires-Dist: wordcloud<2.0.0,>=1.9.0; extra == "cpu"
Requires-Dist: en_core_web_sm<4.0.0,>=3.5.0; extra == "cpu"
Provides-Extra: gpu
Requires-Dist: sentence-transformers<3.0.0,>=2.2.2; extra == "gpu"
Requires-Dist: transformers<5.0.0,>=4.28.0; extra == "gpu"
Requires-Dist: torch<3.0.0,>=2.0.0; extra == "gpu"
Requires-Dist: plotly<6.0.0,>=5.14.0; extra == "gpu"
Requires-Dist: umap-learn<0.6.0,>=0.5.3; extra == "gpu"
Requires-Dist: hdbscan<0.9.0,>=0.8.29; extra == "gpu"
Requires-Dist: bertopic<0.16.0,>=0.15.0; extra == "gpu"
Requires-Dist: gensim<5.0.0,>=4.3.0; extra == "gpu"
Requires-Dist: spacy<4.0.0,>=3.5.0; extra == "gpu"
Requires-Dist: wordcloud<2.0.0,>=1.9.0; extra == "gpu"
Requires-Dist: en_core_web_sm<4.0.0,>=3.5.0; extra == "gpu"
Requires-Dist: bitsandbytes<1.0.0,>=0.41.0; extra == "gpu"
Requires-Dist: accelerate<1.0.0,>=0.20.0; extra == "gpu"
Requires-Dist: safetensors<0.4.0,>=0.3.1; extra == "gpu"
Provides-Extra: web
Requires-Dist: dash<3.0.0,>=2.10.0; extra == "web"
Requires-Dist: dash-bootstrap-components<2.0.0,>=1.5.0; extra == "web"
Requires-Dist: plotly<6.0.0,>=5.14.0; extra == "web"
Provides-Extra: embeddings
Requires-Dist: sentence-transformers<3.0.0,>=2.2.2; extra == "embeddings"
Requires-Dist: transformers<5.0.0,>=4.28.0; extra == "embeddings"
Requires-Dist: torch<3.0.0,>=2.0.0; extra == "embeddings"
Provides-Extra: embeddings-gpu
Requires-Dist: sentence-transformers<3.0.0,>=2.2.2; extra == "embeddings-gpu"
Requires-Dist: transformers<5.0.0,>=4.28.0; extra == "embeddings-gpu"
Requires-Dist: torch<3.0.0,>=2.0.0; extra == "embeddings-gpu"
Requires-Dist: accelerate<1.0.0,>=0.20.0; extra == "embeddings-gpu"
Requires-Dist: bitsandbytes<1.0.0,>=0.41.0; extra == "embeddings-gpu"
Provides-Extra: lda
Requires-Dist: gensim<5.0.0,>=4.3.0; extra == "lda"
Provides-Extra: viz
Requires-Dist: plotly<6.0.0,>=5.14.0; extra == "viz"
Requires-Dist: umap-learn<0.6.0,>=0.5.3; extra == "viz"
Provides-Extra: clustering
Requires-Dist: hdbscan<0.9.0,>=0.8.29; extra == "clustering"
Provides-Extra: nlp
Requires-Dist: spacy<4.0.0,>=3.5.0; extra == "nlp"
Provides-Extra: active
Requires-Dist: cleanlab<3.0.0,>=2.3.0; extra == "active"
Provides-Extra: additional-models
Requires-Dist: bertopic<0.16.0,>=0.15.0; extra == "additional-models"
Requires-Dist: top2vec<2.0.0,>=1.0.27; extra == "additional-models"
Requires-Dist: contextualized-topic-models<3.0.0,>=2.5.0; extra == "additional-models"
Provides-Extra: simple-models
Requires-Dist: scikit-learn<2.0.0,>=1.2.0; extra == "simple-models"
Provides-Extra: optimization
Requires-Dist: polars<1.15.0,>=1.11.0; extra == "optimization"
Requires-Dist: pyarrow>=11.0.0; extra == "optimization"
Provides-Extra: memory-efficient
Requires-Dist: optimum<2.0.0,>=1.15.0; extra == "memory-efficient"
Requires-Dist: bitsandbytes<1.0.0,>=0.41.0; extra == "memory-efficient"
Provides-Extra: minimal
Requires-Dist: sentence-transformers<3.0.0,>=2.2.2; extra == "minimal"
Requires-Dist: transformers<5.0.0,>=4.28.0; extra == "minimal"
Requires-Dist: torch<3.0.0,>=2.0.0; extra == "minimal"
Requires-Dist: plotly<6.0.0,>=5.14.0; extra == "minimal"
Requires-Dist: umap-learn<0.6.0,>=0.5.3; extra == "minimal"
Requires-Dist: hdbscan<0.9.0,>=0.8.29; extra == "minimal"
Requires-Dist: bertopic<0.16.0,>=0.15.0; extra == "minimal"
Requires-Dist: gensim<5.0.0,>=4.3.0; extra == "minimal"
Requires-Dist: spacy<4.0.0,>=3.5.0; extra == "minimal"
Requires-Dist: wordcloud<2.0.0,>=1.9.0; extra == "minimal"
Provides-Extra: spacy-model
Requires-Dist: en_core_web_sm<4.0.0,>=3.5.0; extra == "spacy-model"
Provides-Extra: llm
Requires-Dist: transformers<5.0.0,>=4.28.0; extra == "llm"
Requires-Dist: torch<3.0.0,>=2.0.0; extra == "llm"
Requires-Dist: tqdm<5.0.0,>=4.65.0; extra == "llm"
Requires-Dist: accelerate<0.22.0,>=0.20.0; extra == "llm"
Provides-Extra: llm-openai
Requires-Dist: openai<2.0.0,>=1.0.0; extra == "llm-openai"
Requires-Dist: tqdm<5.0.0,>=4.65.0; extra == "llm-openai"
Provides-Extra: llm-multi
Requires-Dist: openai<2.0.0,>=1.0.0; extra == "llm-multi"
Requires-Dist: google-generativeai>=0.3.0; extra == "llm-multi"
Requires-Dist: anthropic>=0.8.0; extra == "llm-multi"
Requires-Dist: huggingface_hub>=0.20.0; extra == "llm-multi"
Requires-Dist: boto3>=1.28.0; extra == "llm-multi"
Requires-Dist: tqdm<5.0.0,>=4.65.0; extra == "llm-multi"
Provides-Extra: full
Requires-Dist: sentence-transformers<3.0.0,>=2.2.2; extra == "full"
Requires-Dist: transformers<5.0.0,>=4.28.0; extra == "full"
Requires-Dist: torch<3.0.0,>=2.0.0; extra == "full"
Requires-Dist: gensim<5.0.0,>=4.3.0; extra == "full"
Requires-Dist: plotly<6.0.0,>=5.14.0; extra == "full"
Requires-Dist: umap-learn<0.6.0,>=0.5.3; extra == "full"
Requires-Dist: hdbscan<0.9.0,>=0.8.29; extra == "full"
Requires-Dist: spacy<4.0.0,>=3.5.0; extra == "full"
Requires-Dist: en_core_web_sm<4.0.0,>=3.5.0; extra == "full"
Requires-Dist: cleanlab<3.0.0,>=2.3.0; extra == "full"
Requires-Dist: polars<1.15.0,>=1.11.0; extra == "full"
Requires-Dist: bertopic<0.16.0,>=0.15.0; extra == "full"
Requires-Dist: top2vec<2.0.0,>=1.0.27; extra == "full"
Requires-Dist: wordcloud<2.0.0,>=1.9.0; extra == "full"
Requires-Dist: openai<2.0.0,>=1.0.0; extra == "full"
Requires-Dist: tqdm<5.0.0,>=4.65.0; extra == "full"
Provides-Extra: full-gpu
Requires-Dist: sentence-transformers<3.0.0,>=2.2.2; extra == "full-gpu"
Requires-Dist: transformers<5.0.0,>=4.28.0; extra == "full-gpu"
Requires-Dist: torch<3.0.0,>=2.0.0; extra == "full-gpu"
Requires-Dist: accelerate<1.0.0,>=0.20.0; extra == "full-gpu"
Requires-Dist: bitsandbytes<1.0.0,>=0.41.0; extra == "full-gpu"
Requires-Dist: gensim<5.0.0,>=4.3.0; extra == "full-gpu"
Requires-Dist: plotly<6.0.0,>=5.14.0; extra == "full-gpu"
Requires-Dist: umap-learn<0.6.0,>=0.5.3; extra == "full-gpu"
Requires-Dist: hdbscan<0.9.0,>=0.8.29; extra == "full-gpu"
Requires-Dist: spacy<4.0.0,>=3.5.0; extra == "full-gpu"
Requires-Dist: en_core_web_sm<4.0.0,>=3.5.0; extra == "full-gpu"
Requires-Dist: cleanlab<3.0.0,>=2.3.0; extra == "full-gpu"
Requires-Dist: polars<1.15.0,>=1.11.0; extra == "full-gpu"
Requires-Dist: bertopic<0.16.0,>=0.15.0; extra == "full-gpu"
Requires-Dist: top2vec<2.0.0,>=1.0.27; extra == "full-gpu"
Requires-Dist: wordcloud<2.0.0,>=1.9.0; extra == "full-gpu"
Requires-Dist: openai<2.0.0,>=1.0.0; extra == "full-gpu"
Requires-Dist: tqdm<5.0.0,>=4.65.0; extra == "full-gpu"
Provides-Extra: dev
Requires-Dist: black<24.0.0,>=23.3.0; extra == "dev"
Requires-Dist: ruff<0.1.0,>=0.0.265; extra == "dev"
Requires-Dist: mypy<2.0.0,>=1.3.0; extra == "dev"
Provides-Extra: test
Requires-Dist: pytest<8.0.0,>=7.3.1; extra == "test"
Requires-Dist: pytest-cov<5.0.0,>=4.1.0; extra == "test"
Requires-Dist: hypothesis<7.0.0,>=6.75.0; extra == "test"
Provides-Extra: docs
Requires-Dist: sphinx<8.0.0,>=7.0.0; extra == "docs"
Requires-Dist: sphinx-rtd-theme<2.0.0,>=1.2.0; extra == "docs"
Requires-Dist: jupyter<2.0.0,>=1.0.0; extra == "docs"
Dynamic: author
Dynamic: home-page
Dynamic: license-file
Dynamic: requires-python
